{"5167f7c71535600a353c42dca9c39857":{"statistic":{"failed":0,"broken":1,"skipped":0,"passed":0,"unknown":0,"total":1},"items":[{"uid":"807172fcb98b5cfb","reportUrl":"https://Daria1004.github.io/qa_guru_python_12_lesson_10/4//#testresult/807172fcb98b5cfb","status":"broken","statusDetails":"selenium.common.exceptions.SessionNotCreatedException: Message: session not created: Chrome failed to start: exited normally.\n  (session not created: DevToolsActivePort file doesn't exist)\n  (The process started from chrome location /usr/bin/google-chrome is no longer running, so ChromeDriver is assuming that Chrome has crashed.)\nStacktrace:\n#0 0x55c418aa4863 <unknown>\n#1 0x55c41879a8c6 <unknown>\n#2 0x55c4187ced34 <unknown>\n#3 0x55c4187cad3d <unknown>\n#4 0x55c418813aed <unknown>\n#5 0x55c418807343 <unknown>\n#6 0x55c4187d8593 <unknown>\n#7 0x55c4187d8f5e <unknown>\n#8 0x55c418a6884b <unknown>\n#9 0x55c418a6c7a5 <unknown>\n#10 0x55c418a56571 <unknown>\n#11 0x55c418a6d332 <unknown>\n#12 0x55c418a3b87f <unknown>\n#13 0x55c418a93728 <unknown>\n#14 0x55c418a938fb <unknown>\n#15 0x55c418aa39b4 <unknown>\n#16 0x7fa63c094ac3 <unknown>","time":{"start":1713791743181,"stop":1713791756226,"duration":13045}}]},"7c7c5e5f20fe2663d33f122f5ce2ca5a":{"statistic":{"failed":0,"broken":1,"skipped":0,"passed":0,"unknown":0,"total":1},"items":[{"uid":"9ed3bd1f068174a5","reportUrl":"https://Daria1004.github.io/qa_guru_python_12_lesson_10/4//#testresult/9ed3bd1f068174a5","status":"broken","statusDetails":"selenium.common.exceptions.SessionNotCreatedException: Message: session not created: Chrome failed to start: exited normally.\n  (session not created: DevToolsActivePort file doesn't exist)\n  (The process started from chrome location /usr/bin/google-chrome is no longer running, so ChromeDriver is assuming that Chrome has crashed.)\nStacktrace:\n#0 0x555fe15f5863 <unknown>\n#1 0x555fe12eb8c6 <unknown>\n#2 0x555fe131fd34 <unknown>\n#3 0x555fe131bd3d <unknown>\n#4 0x555fe1364aed <unknown>\n#5 0x555fe1358343 <unknown>\n#6 0x555fe1329593 <unknown>\n#7 0x555fe1329f5e <unknown>\n#8 0x555fe15b984b <unknown>\n#9 0x555fe15bd7a5 <unknown>\n#10 0x555fe15a7571 <unknown>\n#11 0x555fe15be332 <unknown>\n#12 0x555fe158c87f <unknown>\n#13 0x555fe15e4728 <unknown>\n#14 0x555fe15e48fb <unknown>\n#15 0x555fe15f49b4 <unknown>\n#16 0x7f2ee9a94ac3 <unknown>","time":{"start":1713791756315,"stop":1713791756491,"duration":176}}]},"fd62217c3385a97c3b02a331591880c0":{"statistic":{"failed":0,"broken":1,"skipped":0,"passed":0,"unknown":0,"total":1},"items":[{"uid":"3027f2bcc161c7fa","reportUrl":"https://Daria1004.github.io/qa_guru_python_12_lesson_10/4//#testresult/3027f2bcc161c7fa","status":"broken","statusDetails":"selenium.common.exceptions.SessionNotCreatedException: Message: session not created: Chrome failed to start: exited normally.\n  (session not created: DevToolsActivePort file doesn't exist)\n  (The process started from chrome location /usr/bin/google-chrome is no longer running, so ChromeDriver is assuming that Chrome has crashed.)\nStacktrace:\n#0 0x55954a2e8863 <unknown>\n#1 0x559549fde8c6 <unknown>\n#2 0x55954a012d34 <unknown>\n#3 0x55954a00ed3d <unknown>\n#4 0x55954a057aed <unknown>\n#5 0x55954a04b343 <unknown>\n#6 0x55954a01c593 <unknown>\n#7 0x55954a01cf5e <unknown>\n#8 0x55954a2ac84b <unknown>\n#9 0x55954a2b07a5 <unknown>\n#10 0x55954a29a571 <unknown>\n#11 0x55954a2b1332 <unknown>\n#12 0x55954a27f87f <unknown>\n#13 0x55954a2d7728 <unknown>\n#14 0x55954a2d78fb <unknown>\n#15 0x55954a2e79b4 <unknown>\n#16 0x7f71db294ac3 <unknown>","time":{"start":1713791756553,"stop":1713791756729,"duration":176}}]},"c523cdf50b1089ff2e96a47805a8515c":{"statistic":{"failed":0,"broken":0,"skipped":0,"passed":1,"unknown":0,"total":1},"items":[{"uid":"b8cbf2da2fd33853","reportUrl":"https://Daria1004.github.io/qa_guru_python_12_lesson_10/4//#testresult/b8cbf2da2fd33853","status":"passed","time":{"start":1713791743179,"stop":1713791743180,"duration":1}}]},"ccd01939447b33c000e3c641ad15f597":{"statistic":{"failed":0,"broken":0,"skipped":0,"passed":1,"unknown":0,"total":1},"items":[{"uid":"688f617c715dd163","reportUrl":"https://Daria1004.github.io/qa_guru_python_12_lesson_10/4//#testresult/688f617c715dd163","status":"passed","time":{"start":1713791743178,"stop":1713791743178,"duration":0}}]},"a5b9628e7aa5b269762a622087644994":{"statistic":{"failed":0,"broken":0,"skipped":0,"passed":1,"unknown":0,"total":1},"items":[{"uid":"faff1d3d34581dd5","reportUrl":"https://Daria1004.github.io/qa_guru_python_12_lesson_10/4//#testresult/faff1d3d34581dd5","status":"passed","time":{"start":1713791743175,"stop":1713791743176,"duration":1}}]}}